<?xml version="1.0" encoding="UTF-8"?>
<databaseChangeLog 
    xmlns="http://www.liquibase.org/xml/ns/dbchangelog"
    xmlns:xsi="http://www.w3.org/2001/XMLSchema-instance"
    xsi:schemaLocation="http://www.liquibase.org/xml/ns/dbchangelog http://www.liquibase.org/xml/ns/dbchangelog/dbchangelog-2.0.xsd">
    
    <changeSet author="talend" id="zoop">
       <sql>

	
CREATE TABLE zoop
(
  measurement bigserial NOT NULL,
  route_code text,
  start_port text,
  end_port text,
  route_frequency text,
  route_start_date  date,
  vessel_name text,
  trip_code text,
  "TIME"  timestamp with time zone,
  geom geometry,
  taxon_name text,
  family character varying,
  genus character varying,
  species character varying,
  sex character varying,
  life_stage character varying,
  taxon_group character varying,
  taxon_eco_group character varying,
  caab_code bigint,
  taxon_start_date date,
  taxon_per_m3 real,
  zoop_comments character varying,
  acknowledgements text,
  longitude double precision,
  latitude double precision,
  CONSTRAINT measurements_zoop_pkey PRIMARY KEY (measurement)
)
       </sql>


        <sql>
ALTER TABLE zoop
ALTER COLUMN geom TYPE geometry(GEOMETRY, 4326)
USING ST_SetSRID(geom,4326);
ALTER TABLE zoop ADD CHECK (ST_IsValid(geom));
CREATE INDEX zoop_gist_idx ON zoop USING GIST (geom); 
	</sql>
    </changeSet>


    <changeSet author="talend" id="zoop_update_schema">
      <sql>
        ALTER TABLE zoop
          ADD COLUMN aphiaid text ;  
      </sql>
    </changeSet>
        
</databaseChangeLog>
