<?xml version="1.1" encoding="UTF-8"?>
<xmi:XMI xmi:version="2.0" xmlns:xmi="http://www.omg.org/XMI" xmlns:expression="http:///expression.ecore">
  <expression:EMFExpression id="null=>" expression="if (profile_measurements.DOXY_QC != null)&#xA;{&#xA;    Var.var1 = null;&#xA;}&#xA;else&#xA;{&#xA;&#x9;Var.var1 = profile_measurements.DOXY_QC.charAt(Var.index);&#xA;} ">
    <variables name="profile_measurements.N_PROF" value="null" talendType="id_Integer" nullable="true"/>
    <variables name="profile_measurements.N_LEVELS" value="null" talendType="id_Integer" nullable="true"/>
    <variables name="profile_measurements.PRES" value="null" talendType="id_Float" nullable="true"/>
    <variables name="profile_measurements.PRES_QC" value="null" talendType="id_String" nullable="true"/>
    <variables name="profile_measurements.PRES_ADJUSTED" value="null" talendType="id_Float" nullable="true"/>
    <variables name="profile_measurements.PRES_ADJUSTED_QC" value="null" talendType="id_String" nullable="true"/>
    <variables name="profile_measurements.PRES_ADJUSTED_ERROR" value="null" talendType="id_Float" nullable="true"/>
    <variables name="profile_measurements.TEMP" value="null" talendType="id_Float" nullable="true"/>
    <variables name="profile_measurements.TEMP_QC" value="null" talendType="id_String" nullable="true"/>
    <variables name="profile_measurements.TEMP_ADJUSTED" value="null" talendType="id_Float" nullable="true"/>
    <variables name="profile_measurements.TEMP_ADJUSTED_QC" value="null" talendType="id_String" nullable="true"/>
    <variables name="profile_measurements.TEMP_ADJUSTED_ERROR" value="null" talendType="id_Float" nullable="true"/>
    <variables name="profile_measurements.PSAL" value="null" talendType="id_Float" nullable="true"/>
    <variables name="profile_measurements.PSAL_QC" value="null" talendType="id_String" nullable="true"/>
    <variables name="profile_measurements.PSAL_ADJUSTED" value="null" talendType="id_Float" nullable="true"/>
    <variables name="profile_measurements.PSAL_ADJUSTED_QC" value="null" talendType="id_String" nullable="true"/>
    <variables name="profile_measurements.PSAL_ADJUSTED_ERROR" value="null" talendType="id_Float" nullable="true"/>
    <variables name="profile_measurements.DOXY" value="null" talendType="id_Float" nullable="true"/>
    <variables name="profile_measurements.DOXY_ADJUSTED" value="null" talendType="id_Float" nullable="true"/>
    <variables name="profile_measurements.DOXY_QC" value="null" talendType="id_Character" nullable="true"/>
    <variables name="profile_measurements.DOXY_ADJUSTED_QC" value="null" talendType="id_Character" nullable="true"/>
    <variables name="profile_measurements.DOXY_ADJUSTED_ERROR" value="null" talendType="id_Float" nullable="true"/>
    <variables name="profile_measurements.TEMP_DOXY" value="null" talendType="id_Float" nullable="true"/>
    <variables name="profile_measurements.TEMP_DOXY_ADJUSTED" value="null" talendType="id_Float" nullable="true"/>
    <variables name="profile_measurements.TEMP_DOXY_QC" value="null" talendType="id_String" nullable="true"/>
    <variables name="profile_measurements.TEMP_DOXY_ADJUSTED_QC" value="null" talendType="id_String" nullable="true"/>
    <variables name="profile_measurements.TEMP_DOXY_ADJUSTED_ERROR" value="null" talendType="id_Float" nullable="true"/>
    <variables name="context.qc_index++" value="0" talendType="id_Integer"/>
    <variables name="if (variableName != null)&#xA;{&#xA;    //Do something if the variable doesn't have a value&#xA;}&#xA;else&#xA;{&#xA;    //Do something if the variable is declared.&#xA;} " value="null" talendType="id_String"/>
  </expression:EMFExpression>
  <expression:EMFExpression id="null=>Var=>DOXY_ADJUSTED_QC" expression="(profile_measurements.DOXY_ADJUSTED_QC == null) ? '\0' : profile_measurements.DOXY_ADJUSTED_QC.charAt(Var.index) ">
    <variables name="profile_measurements.N_PROF" value="null" talendType="id_Integer" nullable="true"/>
    <variables name="profile_measurements.N_LEVELS" value="null" talendType="id_Integer" nullable="true"/>
    <variables name="profile_measurements.PRES" value="null" talendType="id_Float" nullable="true"/>
    <variables name="profile_measurements.PRES_QC" value="null" talendType="id_String" nullable="true"/>
    <variables name="profile_measurements.PRES_ADJUSTED" value="null" talendType="id_Float" nullable="true"/>
    <variables name="profile_measurements.PRES_ADJUSTED_QC" value="null" talendType="id_String" nullable="true"/>
    <variables name="profile_measurements.PRES_ADJUSTED_ERROR" value="null" talendType="id_Float" nullable="true"/>
    <variables name="profile_measurements.TEMP" value="null" talendType="id_Float" nullable="true"/>
    <variables name="profile_measurements.TEMP_QC" value="null" talendType="id_String" nullable="true"/>
    <variables name="profile_measurements.TEMP_ADJUSTED" value="null" talendType="id_Float" nullable="true"/>
    <variables name="profile_measurements.TEMP_ADJUSTED_QC" value="null" talendType="id_String" nullable="true"/>
    <variables name="profile_measurements.TEMP_ADJUSTED_ERROR" value="null" talendType="id_Float" nullable="true"/>
    <variables name="profile_measurements.PSAL" value="null" talendType="id_Float" nullable="true"/>
    <variables name="profile_measurements.PSAL_QC" value="null" talendType="id_String" nullable="true"/>
    <variables name="profile_measurements.PSAL_ADJUSTED" value="null" talendType="id_Float" nullable="true"/>
    <variables name="profile_measurements.PSAL_ADJUSTED_QC" value="null" talendType="id_String" nullable="true"/>
    <variables name="profile_measurements.PSAL_ADJUSTED_ERROR" value="null" talendType="id_Float" nullable="true"/>
    <variables name="profile_measurements.DOXY" value="null" talendType="id_Float" nullable="true"/>
    <variables name="profile_measurements.DOXY_ADJUSTED" value="null" talendType="id_Float" nullable="true"/>
    <variables name="profile_measurements.DOXY_QC" value="null" talendType="id_String" nullable="true"/>
    <variables name="profile_measurements.DOXY_ADJUSTED_QC" value="null" talendType="id_Character" nullable="true"/>
    <variables name="profile_measurements.DOXY_ADJUSTED_ERROR" value="null" talendType="id_Float" nullable="true"/>
    <variables name="profile_measurements.TEMP_DOXY" value="null" talendType="id_Float" nullable="true"/>
    <variables name="profile_measurements.TEMP_DOXY_ADJUSTED" value="null" talendType="id_Float" nullable="true"/>
    <variables name="profile_measurements.TEMP_DOXY_QC" value="null" talendType="id_Character" nullable="true"/>
    <variables name="profile_measurements.TEMP_DOXY_ADJUSTED_QC" value="null" talendType="id_Character" nullable="true"/>
    <variables name="profile_measurements.TEMP_DOXY_ADJUSTED_ERROR" value="null" talendType="id_Float" nullable="true"/>
    <variables name="context.qc_index++" value="0" talendType="id_Integer"/>
    <variables name="(profile_measurements.DOXY_QC == null) ? '\0' : profile_measurements.DOXY_QC.charAt(Var.index) " value="' '" talendType="id_Character"/>
  </expression:EMFExpression>
  <expression:EMFExpression id="null=>Var=>TEMP_DOXY_QC" expression="(profile_measurements.TEMP_DOXY_QC == null) ? '\0' : profile_measurements.TEMP_DOXY_QC.charAt(Var.index)  ">
    <variables name="profile_measurements.N_PROF" value="null" talendType="id_Integer" nullable="true"/>
    <variables name="profile_measurements.N_LEVELS" value="null" talendType="id_Integer" nullable="true"/>
    <variables name="profile_measurements.PRES" value="null" talendType="id_Float" nullable="true"/>
    <variables name="profile_measurements.PRES_QC" value="null" talendType="id_String" nullable="true"/>
    <variables name="profile_measurements.PRES_ADJUSTED" value="null" talendType="id_Float" nullable="true"/>
    <variables name="profile_measurements.PRES_ADJUSTED_QC" value="null" talendType="id_String" nullable="true"/>
    <variables name="profile_measurements.PRES_ADJUSTED_ERROR" value="null" talendType="id_Float" nullable="true"/>
    <variables name="profile_measurements.TEMP" value="null" talendType="id_Float" nullable="true"/>
    <variables name="oat&quot; nullable=&quot;true&quot;/>&#xA;    &lt;" value=" nam" talendType="id_String" nullable="true"/>
    <variables name="profile_measurements.TEMP_ADJUSTED" value="null" talendType="id_Float" nullable="true"/>
    <variables name="profile_measurements.TEMP_ADJUSTED_QC" value="null" talendType="id_String" nullable="true"/>
    <variables name="profile_measurements.TEMP_ADJUSTED_ERROR" value="null" talendType="id_Float" nullable="true"/>
    <variables name="profile_measurements.PSAL" value="null" talendType="id_Float" nullable="true"/>
    <variables name="profile_measurements.PSAL_QC" value="null" talendType="id_String" nullable="true"/>
    <variables name="profile_measurements.PSAL_ADJUSTED" value="null" talendType="id_Float" nullable="true"/>
    <variables name="profile_measurements.PSAL_ADJUSTED_QC" value="null" talendType="id_String" nullable="true"/>
    <variables name="profile_measurements.PSAL_ADJUSTED_ERROR" value="null" talendType="id_Float" nullable="true"/>
    <variables name="profile_measurements.DOXY" value="null" talendType="id_Float" nullable="true"/>
    <variables name="profile_measurements.DOXY_ADJUSTED" value="null" talendType="id_Float" nullable="true"/>
    <variables name="profile_measurements.DOXY_QC" value="null" talendType="id_String" nullable="true"/>
    <variables name="x++&quot; value=&quot;0&quot; talendType=&quot;id_Integer" value="vari" talendType="id_Character" nullable="true"/>
    <variables name="profile_measurements.DOXY_ADJUSTED_ERROR" value="null" talendType="id_Float" nullable="true"/>
    <variables name="profile_measurements.TEMP_DOXY" value="null" talendType="id_Float" nullable="true"/>
    <variables name="profile_measurements.TEMP_DOXY_ADJUSTED" value="null" talendType="id_Float" nullable="true"/>
    <variables name="profile_measurements.TEMP_DOXY_QC" value="null" talendType="id_Character" nullable="true"/>
    <variables name="profile_measurements.TEMP_DOXY_ADJUSTED_QC" value="null" talendType="id_Character" nullable="true"/>
    <variables name="profile_measurements.TEMP_DOXY_ADJUSTED_ERROR" value="null" talendType="id_Float" nullable="true"/>
    <variables name="context.qc_index++" value="0" talendType="id_Integer"/>
    <variables name="(profile_measurements.DOXY_QC == null) ? '\0' : profile_measurements.DOXY_QC.charAt(Var.index) " value="' '" talendType="id_Character"/>
    <variables name="(profile_measurements.DOXY_ADJUSTED_QC == null) ? '\0' : profile_measurements.DOXY_ADJUSTED_QC.charAt(Var.index)  " value="' '" talendType="id_Character"/>
  </expression:EMFExpression>
  <expression:EMFExpression id="null=>Var=>TEMP_DOXY_ADJUSTED_QC" expression="(profile_measurements.TEMP_DOXY_ADJUSTED_QC == null) ? '\0' : profile_measurements.TEMP_DOXY_ADJUSTED_QC.charAt(Var.index)  ">
    <variables name="profile_measurements.N_PROF" value="null" talendType="id_Integer" nullable="true"/>
    <variables name="profile_measurements.N_LEVELS" value="null" talendType="id_Integer" nullable="true"/>
    <variables name="profile_measurements.PRES" value="null" talendType="id_Float" nullable="true"/>
    <variables name="profile_measurements.PRES_QC" value="null" talendType="id_String" nullable="true"/>
    <variables name="profile_measurements.PRES_ADJUSTED" value="null" talendType="id_Float" nullable="true"/>
    <variables name="profile_measurements.PRES_ADJUSTED_QC" value="null" talendType="id_String" nullable="true"/>
    <variables name="profile_measurements.PRES_ADJUSTED_ERROR" value="null" talendType="id_Float" nullable="true"/>
    <variables name="profile_measurements.TEMP" value="null" talendType="id_Float" nullable="true"/>
    <variables name="profile_measurements.TEMP_QC" value="null" talendType="id_String" nullable="true"/>
    <variables name="profile_measurements.TEMP_ADJUSTED" value="null" talendType="id_Float" nullable="true"/>
    <variables name="profile_measurements.TEMP_ADJUSTED_QC" value="null" talendType="id_String" nullable="true"/>
    <variables name="profile_measurements.TEMP_ADJUSTED_ERROR" value="null" talendType="id_Float" nullable="true"/>
    <variables name="profile_measurements.PSAL" value="null" talendType="id_Float" nullable="true"/>
    <variables name="profile_measurements.PSAL_QC" value="null" talendType="id_String" nullable="true"/>
    <variables name="profile_measurements.PSAL_ADJUSTED" value="null" talendType="id_Float" nullable="true"/>
    <variables name="profile_measurements.PSAL_ADJUSTED_QC" value="null" talendType="id_String" nullable="true"/>
    <variables name="profile_measurements.PSAL_ADJUSTED_ERROR" value="null" talendType="id_Float" nullable="true"/>
    <variables name="profile_measurements.DOXY" value="null" talendType="id_Float" nullable="true"/>
    <variables name="profile_measurements.DOXY_ADJUSTED" value="null" talendType="id_Float" nullable="true"/>
    <variables name="profile_measurements.DOXY_QC" value="null" talendType="id_String" nullable="true"/>
    <variables name="profile_measurements.DOXY_ADJUSTED_QC" value="null" talendType="id_Character" nullable="true"/>
    <variables name="profile_measurements.DOXY_ADJUSTED_ERROR" value="null" talendType="id_Float" nullable="true"/>
    <variables name="profile_measurements.TEMP_DOXY" value="null" talendType="id_Float" nullable="true"/>
    <variables name="profile_measurements.TEMP_DOXY_ADJUSTED" value="null" talendType="id_Float" nullable="true"/>
    <variables name="profile_measurements.TEMP_DOXY_QC" value="null" talendType="id_Character" nullable="true"/>
    <variables name="profile_measurements.TEMP_DOXY_ADJUSTED_QC" value="null" talendType="id_Character" nullable="true"/>
    <variables name="profile_measurements.TEMP_DOXY_ADJUSTED_ERROR" value="null" talendType="id_Float" nullable="true"/>
    <variables name="context.qc_index++" value="0" talendType="id_Integer"/>
    <variables name="(profile_measurements.DOXY_QC == null) ? '\0' : profile_measurements.DOXY_QC.charAt(Var.index) " value="' '" talendType="id_Character"/>
    <variables name="(profile_measurements.DOXY_ADJUSTED_QC == null) ? '\0' : profile_measurements.DOXY_ADJUSTED_QC.charAt(Var.index)  " value="' '" talendType="id_Character"/>
    <variables name="(profile_measurements.TEMP_DOXY_QC == null) ? '\0' : profile_measurements.TEMP_DOXY_QC.charAt(Var.index)   " value="' '" talendType="id_Character"/>
  </expression:EMFExpression>
  <expression:EMFExpression id="null=>Var=>DOXY_QC" expression="(profile_measurements.DOXY_QC == null) ? '\0' : profile_measurements.DOXY_QC.charAt(Var.index) ">
    <variables name="profile_measurements.N_PROF" value="null" talendType="id_Integer" nullable="true"/>
    <variables name="profile_measurements.N_LEVELS" value="null" talendType="id_Integer" nullable="true"/>
    <variables name="profile_measurements.PRES" value="null" talendType="id_Float" nullable="true"/>
    <variables name="profile_measurements.PRES_QC" value="null" talendType="id_String" nullable="true"/>
    <variables name="profile_measurements.PRES_ADJUSTED" value="null" talendType="id_Float" nullable="true"/>
    <variables name="profile_measurements.PRES_ADJUSTED_QC" value="null" talendType="id_String" nullable="true"/>
    <variables name="profile_measurements.PRES_ADJUSTED_ERROR" value="null" talendType="id_Float" nullable="true"/>
    <variables name="profile_measurements.TEMP" value="null" talendType="id_Float" nullable="true"/>
    <variables name="profile_measurements.TEMP_QC" value="null" talendType="id_String" nullable="true"/>
    <variables name="profile_measurements.TEMP_ADJUSTED" value="null" talendType="id_Float" nullable="true"/>
    <variables name="profile_measurements.TEMP_ADJUSTED_QC" value="null" talendType="id_String" nullable="true"/>
    <variables name="profile_measurements.TEMP_ADJUSTED_ERROR" value="null" talendType="id_Float" nullable="true"/>
    <variables name="profile_measurements.PSAL" value="null" talendType="id_Float" nullable="true"/>
    <variables name="profile_measurements.PSAL_QC" value="null" talendType="id_String" nullable="true"/>
    <variables name="profile_measurements.PSAL_ADJUSTED" value="null" talendType="id_Float" nullable="true"/>
    <variables name="profile_measurements.PSAL_ADJUSTED_QC" value="null" talendType="id_String" nullable="true"/>
    <variables name="profile_measurements.PSAL_ADJUSTED_ERROR" value="null" talendType="id_Float" nullable="true"/>
    <variables name="profile_measurements.DOXY" value="null" talendType="id_Float" nullable="true"/>
    <variables name="profile_measurements.DOXY_ADJUSTED" value="null" talendType="id_Float" nullable="true"/>
    <variables name="profile_measurements.DOXY_QC" value="null" talendType="id_String" nullable="true"/>
    <variables name="profile_measurements.DOXY_ADJUSTED_QC" value="null" talendType="id_String" nullable="true"/>
    <variables name="profile_measurements.DOXY_ADJUSTED_ERROR" value="null" talendType="id_Float" nullable="true"/>
    <variables name="profile_measurements.TEMP_DOXY" value="null" talendType="id_Float" nullable="true"/>
    <variables name="profile_measurements.TEMP_DOXY_ADJUSTED" value="null" talendType="id_Float" nullable="true"/>
    <variables name="profile_measurements.TEMP_DOXY_QC" value="null" talendType="id_String" nullable="true"/>
    <variables name="profile_measurements.TEMP_DOXY_ADJUSTED_QC" value="null" talendType="id_String" nullable="true"/>
    <variables name="profile_measurements.TEMP_DOXY_ADJUSTED_ERROR" value="null" talendType="id_Float" nullable="true"/>
    <variables name="context.qc_index++" value="0" talendType="id_Integer"/>
    <variables name="(profile_measurements.DOXY_QC == null) ? '\0' : profile_measurements.DOXY_QC.charAt(Var.index) " value="' '" talendType="id_Character"/>
    <variables name="(profile_measurements.DOXY_ADJUSTED_QC == null) ? '\0' : profile_measurements.DOXY_ADJUSTED_QC.charAt(Var.index)  " value="' '" talendType="id_Character"/>
    <variables name="(profile_measurements.TEMP_DOXY_QC == null) ? '\0' : profile_measurements.TEMP_DOXY_QC.charAt(Var.index)   " value="' '" talendType="id_Character"/>
    <variables name="(profile_measurements.TEMP_DOXY_ADJUSTED_QC == null) ? '\0' : profile_measurements.TEMP_DOXY_ADJUSTED_QC.charAt(Var.index)   " value="' '" talendType="id_Character"/>
    <variables name="(profile_measurements.PSAL_QC == null) ? '\0' : ( (profile_measurements.PSAL_QC.charAt(Var.index) == ' ') ? '\0' : profile_measurements.PSAL_QC.charAt(Var.index) )     " value="' '" talendType="id_Character"/>
    <variables name="(profile_measurements.DOXY_QC != null) ? '\0' : profile_measurements.DOXY_QC.charAt(Var.index) " value="' '" talendType="id_Character"/>
    <variables name="(if (profile_measurements.DOXY_QC != null)&#xA;{&#xA;&#x9;Var.DOXY_QC = '\0';&#xA;}&#xA;else&#xA;{&#xA;&#x9;Var.DOXY_QC = profile_measurements.DOXY_QC.charAt(Var.index);}&#xA;&#x9;)&#x9;              " value="' '" talendType="id_Character"/>
    <variables name="if (profile_measurements.DOXY_QC != null)&#xA;{&#xA;&#x9;Var.DOXY_QC = '\0';&#xA;}&#xA;else&#xA;{&#xA;&#x9;Var.DOXY_QC = profile_measurements.DOXY_QC.charAt(Var.index);}&#x9;             " value="' '" talendType="id_Character"/>
    <variables name="if (profile_measurements.DOXY_QC != null)&#xA;{&#xA;&#x9;Character Var.DOXY_QC = null;&#xA;}&#xA;else&#xA;{&#xA;&#x9;Var.DOXY_QC = profile_measurements.DOXY_QC.charAt(Var.index);}&#x9;            " value="' '" talendType="id_Character"/>
    <variables name="if (profile_measurements.DOXY_QC != null)&#xA;{&#xA;&#x9;Character Var.DOXY_QC = null;&#xA;}&#xA;else&#xA;{&#xA;&#x9;Var.DOXY_QC = profile_measurements.DOXY_QC.charAt(Var.index);}&#x9;           " value="' '" talendType="id_Character"/>
    <variables name="if (profile_measurements.DOXY_QC != null)&#xA;{&#xA;&#x9;Var.DOXY_QC = '';&#xA;}&#xA;else&#xA;{&#xA;&#x9;Var.DOXY_QC = profile_measurements.DOXY_QC.charAt(Var.index);}&#x9;          " value="' '" talendType="id_Character"/>
    <variables name="if (profile_measurements.DOXY_QC != null)&#xA;{&#xA;&#x9;Var.DOXY_QC = &quot;&quot;;&#xA;}&#xA;else&#xA;{&#xA;&#x9;Var.DOXY_QC = profile_measurements.DOXY_QC.charAt(Var.index);}&#x9;         " value="' '" talendType="id_Character"/>
    <variables name="if (profile_measurements.DOXY_QC != null)&#xA;{&#xA;&#x9;Var.DOXY_QC = &quot;&quot;;&#xA;}&#xA;else&#xA;{&#xA;&#x9;Var.DOXY_QC = profile_measurements.DOXY_QC.charAt(Var.index);}&#x9;        " value="' '" talendType="id_Character"/>
    <variables name="if (profile_measurements.DOXY_QC != null)&#xA;{&#xA;&#x9;Var.DOXY_QC = null;&#xA;}&#xA;else&#xA;{&#xA;&#x9;Var.DOXY_QC = profile_measurements.DOXY_QC.charAt(index);}&#x9;       " value="' '" talendType="id_Character"/>
    <variables name="if (profile_measurements.DOXY_QC != null)&#xA;{&#xA;&#x9;Var.DOXY_QC = null;&#xA;}&#xA;else&#xA;{&#xA;&#x9;Var.DOXY_QC = profile_measurements.DOXY_QC.charAt(index);}&#x9;      " value="' '" talendType="id_Character"/>
    <variables name="if (profile_measurements.DOXY_QC != null)&#xA;{&#xA;&#x9;Var.DOXY_QC = null;&#xA;}&#xA;else&#xA;{&#xA;&#x9;Var.DOXY_QC = profile_measurements.DOXY_QC(index);&#xA;}&#x9;     " value="' '" talendType="id_Character"/>
    <variables name="if (profile_measurements.DOXY_QC != null)&#xA;{&#xA;&#x9;Var.DOXY_QC = null&#xA;}&#xA;else&#xA;{&#xA;&#x9;Var.DOXY_QC = profile_measurements.DOXY_QC(index)};&#x9;    " value="' '" talendType="id_Character"/>
    <variables name="if (profile_measurements.DOXY_QC != null)&#xA;{&#xA;&#x9;Var.DOXY_QC = null&#xA;}&#xA;else&#xA;{&#xA;&#x9;Var.DOXY_QC = profile_measurements.DOXY_QC(index)};&#x9;   " value="' '" talendType="id_Character"/>
    <variables name="if (profile_measurements.DOXY_QC != null)&#xA;{&#xA;&#x9;Var.DOXY_QC = null&#xA;}&#xA;else&#xA;{&#xA;&#x9;Var.DOXY_QC = profile_measurements.DOXY_QC(index)&#xA;}&#x9;&#x9;  " value="' '" talendType="id_Character"/>
    <variables name="if (profile_measurements.DOXY_QC != null)&#xA;{&#xA;&#x9;Var.DOXY_QC = null&#xA;}&#xA;else&#xA;{&#xA;&#x9;Var.DOXY_QC = profile_measurements.DOXY_QC(index);&#xA;}&#x9;&#x9; " value="' '" talendType="id_Character"/>
    <variables name="Var.index" value="5"/>
  </expression:EMFExpression>
  <expression:EMFExpression id="null=>Var=>PSAL_QC" expression="(profile_measurements.PSAL_QC == null) ? '\0' : ( (profile_measurements.PSAL_QC.charAt(Var.index) == ' ') ? '\0' : profile_measurements.PSAL_QC.charAt(Var.index) )     ">
    <variables name="profile_measurements.N_PROF" value="null" talendType="id_Integer" nullable="true"/>
    <variables name="profile_measurements.N_LEVELS" value="null" talendType="id_Integer" nullable="true"/>
    <variables name="profile_measurements.PRES" value="null" talendType="id_Float" nullable="true"/>
    <variables name="profile_measurements.PRES_QC" value="null" talendType="id_String" nullable="true"/>
    <variables name="profile_measurements.PRES_ADJUSTED" value="null" talendType="id_Float" nullable="true"/>
    <variables name="profile_measurements.PRES_ADJUSTED_QC" value="null" talendType="id_String" nullable="true"/>
    <variables name="profile_measurements.PRES_ADJUSTED_ERROR" value="null" talendType="id_Float" nullable="true"/>
    <variables name="profile_measurements.TEMP" value="null" talendType="id_Float" nullable="true"/>
    <variables name="profile_measurements.TEMP_QC" value="null" talendType="id_String" nullable="true"/>
    <variables name="profile_measurements.TEMP_ADJUSTED" value="null" talendType="id_Float" nullable="true"/>
    <variables name="profile_measurements.TEMP_ADJUSTED_QC" value="null" talendType="id_String" nullable="true"/>
    <variables name="profile_measurements.TEMP_ADJUSTED_ERROR" value="null" talendType="id_Float" nullable="true"/>
    <variables name="profile_measurements.PSAL" value="null" talendType="id_Float" nullable="true"/>
    <variables name="profile_measurements.PSAL_QC" value="null" talendType="id_String" nullable="true"/>
    <variables name="profile_measurements.PSAL_ADJUSTED" value="null" talendType="id_Float" nullable="true"/>
    <variables name="profile_measurements.PSAL_ADJUSTED_QC" value="null" talendType="id_String" nullable="true"/>
    <variables name="profile_measurements.PSAL_ADJUSTED_ERROR" value="null" talendType="id_Float" nullable="true"/>
    <variables name="profile_measurements.DOXY" value="null" talendType="id_Float" nullable="true"/>
    <variables name="profile_measurements.DOXY_ADJUSTED" value="null" talendType="id_Float" nullable="true"/>
    <variables name="profile_measurements.DOXY_QC" value="null" talendType="id_String" nullable="true"/>
    <variables name="profile_measurements.DOXY_ADJUSTED_QC" value="null" talendType="id_String" nullable="true"/>
    <variables name="profile_measurements.DOXY_ADJUSTED_ERROR" value="null" talendType="id_Float" nullable="true"/>
    <variables name="profile_measurements.TEMP_DOXY" value="null" talendType="id_Float" nullable="true"/>
    <variables name="profile_measurements.TEMP_DOXY_ADJUSTED" value="null" talendType="id_Float" nullable="true"/>
    <variables name="profile_measurements.TEMP_DOXY_QC" value="null" talendType="id_String" nullable="true"/>
    <variables name="profile_measurements.TEMP_DOXY_ADJUSTED_QC" value="null" talendType="id_String" nullable="true"/>
    <variables name="profile_measurements.TEMP_DOXY_ADJUSTED_ERROR" value="null" talendType="id_Float" nullable="true"/>
    <variables name="context.qc_index++" value="0" talendType="id_Integer"/>
    <variables name="(profile_measurements.DOXY_QC == null) ? '\0' : profile_measurements.DOXY_QC.charAt(Var.index)  " value="' '" talendType="id_Character"/>
    <variables name="(profile_measurements.DOXY_ADJUSTED_QC == null) ? '\0' : profile_measurements.DOXY_ADJUSTED_QC.charAt(Var.index)  " value="' '" talendType="id_Character"/>
    <variables name="(profile_measurements.TEMP_DOXY_QC == null) ? '\0' : profile_measurements.TEMP_DOXY_QC.charAt(Var.index)   " value="' '" talendType="id_Character"/>
    <variables name="(profile_measurements.TEMP_DOXY_ADJUSTED_QC == null) ? '\0' : profile_measurements.TEMP_DOXY_ADJUSTED_QC.charAt(Var.index)   " value="' '" talendType="id_Character"/>
    <variables name="(profile_measurements.PSAL_QC == null) ? '\0' : ( (profile_measurements.PSAL_QC.charAt(Var.index) == ' ') ? '\0' : profile_measurements.PSAL_QC.charAt(Var.index) )     " value="' '" talendType="id_Character"/>
    <variables name="(profile_measurements.DOXY_QC == null) ? '\0' : profile_measurements.DOXY_QC.charAt(Var.index) " value="' '" talendType="id_Character"/>
    <variables name="(profile_measurements.PSAL_QC == null) ? '\0' : ( (profile_measurements.PSAL_QC.charAt(Var.index) == ' ') ? '\0' : profile_measurements.PSAL_QC.charAt(Var.index) )    " value="' '" talendType="id_Character"/>
    <variables name="(profile_measurements.PSAL_QC == null) ? '\0' : ( (profile_measurements.PSAL_QC.charAt(Var.index) == '\0') ? '\0' : profile_measurements.PSAL_QC.charAt(Var.index) )   " value="' '" talendType="id_Character"/>
    <variables name="(profile_measurements.PSAL_QC == null) ? '\0' : ( (profile_measurements.PSAL_QC.charAt(Var.index) == null) ? '\0' : profile_measurements.PSAL_QC.charAt(Var.index) )  " value="' '" talendType="id_Character"/>
    <variables name="(profile_measurements.PSAL_QC == null) ? '\0' : ( (profile_measurements.PSAL_QC.charAt(Var.index)  == null) ? '\0' : profile_measurements.PSAL_QC.charAt(Var.index) ) " value="' '" talendType="id_Character"/>
    <variables name="(profile_measurements.PSAL_QC == null) ? '\0' : profile_measurements.PSAL_QC.charAt(Var.index)    " value="' '" talendType="id_Character"/>
  </expression:EMFExpression>
</xmi:XMI>
